preprocessing/__init__.py
preprocessing/base.py
prepwizard-1.0.1.dist-info/licenses/LICENSE
prepwizard-1.0.1.dist-info/METADATA
prepwizard-1.0.1.dist-info/WHEEL
prepwizard-1.0.1.dist-info/top_level.txt
prepwizard-1.0.1.dist-info/RECORD
